pyvecc/Key.py
pyvecc/Rabbit.py
pyvecc/SecurityViolationException.py
pyvecc/__init__.py
pyvecc/curves.py
pyvecc/eccrypt.py
pyvecc/ecdsa.py
pyvecc/elliptic.py
pyvecc/encoding.py
pyvecc/performance.py
pyvecc/primes.py
pyvecc/shacrypt.py
pyvecc-0.0.2.data/scripts/testecc.py
pyvecc-0.0.2.data/scripts/testecckey.py
pyvecc-0.0.2.data/scripts/testeccperf.py
pyvecc-0.0.2.dist-info/METADATA
pyvecc-0.0.2.dist-info/WHEEL
pyvecc-0.0.2.dist-info/entry_points.txt
pyvecc-0.0.2.dist-info/top_level.txt
pyvecc-0.0.2.dist-info/RECORD
