Metadata-Version: 2.1
Name: pyvecc
Version: 0.0.2
Summary: Pure Python implementation of an elliptic curve cryptosystem based on FIPS 186-3
Home-page: https://github.com/pglen/pyvecc
Author: peterglen99@gmail.com
Author-email: peterglen99@gmail.com
License: MIT
Keywords: simple elliptic curve cryptosystem
Classifier: Development Status :: 4 - Beta
Classifier: Intended Audience :: Developers
Classifier: License :: OSI Approved :: MIT License
Classifier: Topic :: Software Development :: Libraries :: Python Modules
Classifier: Topic :: Communications
Classifier: Topic :: Security :: Cryptography
Classifier: Topic :: Internet
